Lattice_iCEBreaker_v1.1a/8_two_bit_greater_than_detector_proj8/two_bit_greater_than_detector.v
/***************************************************
Engineer: Harrison Warke
Date Created: 25/10/2025
Module Name: two_bit_A_greater_than_B_detector
Project Name: LAoE
Target Device: Lattice ICE40UP5K-SG48

Description: Create a 2bitnumber1 > 2bitnumber2 detector

Truth table below 

A  B  C  D |  Out
0  0  0  0 |   0
0  0  0  1 |   0
0  0  1  0 |   0
0  0  1  1 |   0
0  1  0  0 |   1
0  1  0  1 |   0
0  1  1  0 |   0
0  1  1  1 |   0
1  0  0  0 |   1
1  0  0  1 |   1
1  0  1  0 |   0
1  0  1  1 |   0
1  1  0  0 |   1
1  1  0  1 |   1
1  1  1  0 |   1
1  1  1  1 |   0

***************************************************/

module two_bit_greater_than_detector (
    input IN_A, //MSB of 2bitnumber1
    input IN_B, //LSB of 2bitnumber1
    input IN_C, //MSB of 2bitnumber2
    input IN_D, //LSB of 2bitnumber2
    output OUT
);

assign OUT = ( IN_A & ~IN_C ) | ( (IN_A~^IN_C) & (IN_B & ~IN_D) );


endmodule

Lattice_iCEBreaker_v1.1a/8_two_bit_greater_than_detector_proj8/two_bit_greater_than_detector_tb.v
`timescale 1ns/1ps

module two_bit_greater_than_detector_tb;

    // Testbench signals
    reg tb_IN_A;
    reg tb_IN_B;
    reg tb_IN_C;
    reg tb_IN_D;
    wire tb_OUT;
    

    // Instantiate the module under test
    two_bit_greater_than_detector uut (
        .IN_A(tb_IN_A),
        .IN_B(tb_IN_B),
        .IN_C(tb_IN_C),
        .IN_D(tb_IN_D),
        .OUT(tb_OUT)
    );

    initial begin
        // For GTKWave to dump waveform data
        $dumpfile("two_bit_greater_than_detector.vcd");      // Output VCD file
        $dumpvars(0, two_bit_greater_than_detector_tb); // Dump all variables in this scope

        $display("A  B  C  D | OUT");
        $monitor("%b  %b  %b  %b | %b", 
            tb_IN_A, tb_IN_B, tb_IN_C, tb_IN_D, tb_OUT);
    

        // Test function of two bit greater than detector 
     
        tb_IN_A = 0;
        tb_IN_B = 0;
        tb_IN_C = 0;
        tb_IN_D = 0;
        #10;
        tb_IN_A = 0;
        tb_IN_B = 0;        
        tb_IN_C = 0;
        tb_IN_D = 1;
        #10;
        tb_IN_A = 0;
        tb_IN_B = 0;        
        tb_IN_C = 1;
        tb_IN_D = 0;
        #10;
        tb_IN_A = 0;
        tb_IN_B = 0;        
        tb_IN_C = 1;
        tb_IN_D = 1;
        #10;
        tb_IN_A = 0;
        tb_IN_B = 1;        
        tb_IN_C = 0;
        tb_IN_D = 0;
        #10;
        tb_IN_A = 0;
        tb_IN_B = 1;        
        tb_IN_C = 0;
        tb_IN_D = 1;
        #10;
        tb_IN_A = 0;
        tb_IN_B = 1;        
        tb_IN_C = 1;
        tb_IN_D = 0;
        #10;
        tb_IN_A = 0;
        tb_IN_B = 1;        
        tb_IN_C = 1;
        tb_IN_D = 1;
        #10;
        tb_IN_A = 1;
        tb_IN_B = 0;        
        tb_IN_C = 0;
        tb_IN_D = 0;
        #10;
        tb_IN_A = 1;
        tb_IN_B = 0;        
        tb_IN_C = 0;
        tb_IN_D = 1;
        #10;
        tb_IN_A = 1;
        tb_IN_B = 0;        
        tb_IN_C = 1;
        tb_IN_D = 0;
        #10;
        tb_IN_A = 1;
        tb_IN_B = 0;        
        tb_IN_C = 1;
        tb_IN_D = 1;
        #10;
        tb_IN_A = 1;
        tb_IN_B = 1;        
        tb_IN_C = 0;
        tb_IN_D = 0;
        #10;
        tb_IN_A = 1;
        tb_IN_B = 1;        
        tb_IN_C = 0;
        tb_IN_D = 1;
        #10;
        tb_IN_A = 1;
        tb_IN_B = 1;        
        tb_IN_C = 1;
        tb_IN_D = 0;
        #10;
        tb_IN_A = 1;
        tb_IN_B = 1;        
        tb_IN_C = 1;
        tb_IN_D = 1;
        #10;
        $finish;  // End simulation
    end

endmodule

Lattice_iCEBreaker_v1.1a/8_two_bit_greater_than_detector_proj8/two_bit_greater_than_detector.vcd
$date
	Sat Oct 25 12:23:21 2025
$end
$version
	Icarus Verilog
$end
$timescale
	1ps
$end
$scope module two_bit_greater_than_detector_tb $end
$var wire 1 ! tb_OUT $end
$var reg 1 " tb_IN_A $end
$var reg 1 # tb_IN_B $end
$var reg 1 $ tb_IN_C $end
$var reg 1 % tb_IN_D $end
$scope module uut $end
$var wire 1 " IN_A $end
$var wire 1 # IN_B $end
$var wire 1 $ IN_C $end
$var wire 1 % IN_D $end
$var wire 1 ! OUT $end
$upscope $end
$upscope $end
$enddefinitions $end
$comment Show the parameter values. $end
$dumpall
$end
#0
$dumpvars
0%
0$
0#
0"
0!
$end
#10000
1%
#20000
0%
1$
#30000
1%
#40000
1!
0%
0$
1#
#50000
0!
1%
#60000
0%
1$
#70000
1%
#80000
1!
0%
0$
0#
1"
#90000
1%
#100000
0!
0%
1$
#110000
1%
#120000
1!
0%
0$
1#
#130000
1%
#140000
1!
0%
1$
#150000
0!
1%
