Lattice_iCEBreaker_v1.1a/6_multiplexer_proj6/multiplexer_behavioural.v
/***************************************************
Engineer: Harrison Warke
Date Created: 22/10/2025
Module Name: multiplexer_behavioural
Project Name: LAoE
Target Device: Lattice ICE40UP5K-SG48

Description: Create a 2-1 multiplexer using a conditional operator.

Truth table below 

Sel  A  B |  Out
0    0  0 |   0
0    0  1 |   0
0    1  0 |   1
0    1  1 |   1
1    0  0 |   0
1    0  1 |   1
1    1  0 |   0
1    1  1 |   1

***************************************************/

module multiplexer_behavioural (
    input SEL,
    input IN_A,
    input IN_B,
    output OUTPUT
);

assign OUTPUT = SEL ? IN_B : IN_A;

endmodule

Lattice_iCEBreaker_v1.1a/6_multiplexer_proj6/multiplexer_behavioural_tb.v
`timescale 1ns/1ps

module multiplexer_behavioural_tb;

    // Testbench signals
    reg tb_SEL;
    reg tb_IN_A;
    reg tb_IN_B;
    wire tb_OUTPUT;
    

    // Instantiate the module under test
    multiplexer_behavioural uut (
        .SEL(tb_SEL),
        .IN_A(tb_IN_A),
        .IN_B(tb_IN_B),
        .OUTPUT(tb_OUTPUT)
    );

    initial begin
        // For GTKWave to dump waveform data
        $dumpfile("multiplexer_behavioural.vcd");      // Output VCD file
        $dumpvars(0, multiplexer_behavioural_tb); // Dump all variables in this scope

        $display("Sel A B  | OUT");
        $monitor("%b  %b  %b |  %b", 
            tb_SEL, tb_IN_A, tb_IN_B, tb_OUTPUT);
    

        // Test function of 2-1 multiplexer
        tb_SEL = 0;
        tb_IN_A = 0;
        tb_IN_B = 0;
        #10;
        tb_SEL = 0;
        tb_IN_A = 0;
        tb_IN_B = 1;
        #10;
        tb_SEL = 0;
        tb_IN_A = 1;
        tb_IN_B = 0;
        #10;
        tb_SEL = 0;
        tb_IN_A = 1;
        tb_IN_B = 1;
        #10
        tb_SEL = 1;
        tb_IN_A = 0;
        tb_IN_B = 0;
        #10;
        tb_SEL = 1;
        tb_IN_A = 0;
        tb_IN_B = 1;
        #10
        tb_SEL = 1;
        tb_IN_A = 1;
        tb_IN_B = 0;
        #10
        tb_SEL = 1;
        tb_IN_A = 1;
        tb_IN_B = 1;
        #10

        $finish;  // End simulation
    end

endmodule

Lattice_iCEBreaker_v1.1a/6_multiplexer_proj6/multiplexer_behavioural.vcd
$date
	Wed Oct 22 08:57:18 2025
$end
$version
	Icarus Verilog
$end
$timescale
	1ps
$end
$scope module multiplexer_behavioural_tb $end
$var wire 1 ! tb_OUTPUT $end
$var reg 1 " tb_IN_A $end
$var reg 1 # tb_IN_B $end
$var reg 1 $ tb_SEL $end
$scope module uut $end
$var wire 1 " IN_A $end
$var wire 1 # IN_B $end
$var wire 1 $ SEL $end
$var wire 1 ! OUTPUT $end
$upscope $end
$upscope $end
$enddefinitions $end
$comment Show the parameter values. $end
$dumpall
$end
#0
$dumpvars
0$
0#
0"
0!
$end
#10000
1#
#20000
1!
0#
1"
#30000
1#
#40000
0!
0#
0"
1$
#50000
1!
1#
#60000
0!
0#
1"
#70000
1!
1#
