Lattice_iCEBreaker_v1.1a/5_multiplexer_proj5/two_to_one_multiplexer.v
/***************************************************
Engineer: Harrison Warke
Date Created: 21/10/2025
Module Name: Simple Multiplexer 
Project Name: LAoE
Target Device: Lattice ICE40UP5K-SG48

Description: Create a 2-1 multiplexer out of logic gates

Truth table below 

Sel  A  B |  Out
0    0  0 |   0
0    0  1 |   0
0    1  0 |   1
0    1  1 |   1
1    0  0 |   0
1    0  1 |   1
1    1  0 |   0
1    1  1 |   1

***************************************************/

module two_to_one_multiplexer (
    input sel,
    input a,
    input b,
    output out
);

assign out = (sel & b) | (~sel & a);

endmodule

Lattice_iCEBreaker_v1.1a/5_multiplexer_proj5/two_to_one_multiplexer_tb.v
`timescale 1ns/1ps

module two_to_one_multiplexer_tb;

    // Testbench signals
    reg tb_sel;
    reg tb_a;
    reg tb_b;
    wire tb_out;
    

    // Instantiate the module under test
    two_to_one_multiplexer uut (
        .sel(tb_sel),
        .a(tb_a),
        .b(tb_b),
        .out(tb_out)
    );

    initial begin
        // For GTKWave to dump waveform data
        $dumpfile("two_to_one_multiplexer.vcd");      // Output VCD file
        $dumpvars(0, two_to_one_multiplexer_tb); // Dump all variables in this scope

        $display("Sel A B  | OUT");
        $monitor("%b  %b  %b |  %b", 
            tb_sel, tb_a, tb_b, tb_out);
    

        // Test function of 2-1 multiplexer
        tb_sel = 0;
        tb_a = 0;
        tb_b = 0;
        #10;
        tb_sel = 0;
        tb_a = 0;
        tb_b = 1;
        #10;
        tb_sel = 0;
        tb_a = 1;
        tb_b = 0;
        #10;
        tb_sel = 0;
        tb_a = 1;
        tb_b = 1;
        #10
        tb_sel = 1;
        tb_a = 0;
        tb_b = 0;
        #10;
        tb_sel = 1;
        tb_a = 0;
        tb_b = 1;
        #10
        tb_sel = 1;
        tb_a = 1;
        tb_b = 0;
        #10
        tb_sel = 1;
        tb_a = 1;
        tb_b = 1;
        #10

        $finish;  // End simulation
    end

endmodule

Lattice_iCEBreaker_v1.1a/5_multiplexer_proj5/two_to_one_multiplexer.vcd
$date
	Tue Oct 21 09:06:59 2025
$end
$version
	Icarus Verilog
$end
$timescale
	1ps
$end
$scope module two_to_one_multiplexer_tb $end
$var wire 1 ! tb_out $end
$var reg 1 " tb_a $end
$var reg 1 # tb_b $end
$var reg 1 $ tb_sel $end
$scope module uut $end
$var wire 1 " a $end
$var wire 1 # b $end
$var wire 1 ! out $end
$var wire 1 $ sel $end
$upscope $end
$upscope $end
$enddefinitions $end
$comment Show the parameter values. $end
$dumpall
$end
#0
$dumpvars
0$
0#
0"
0!
$end
#10000
1#
#20000
1!
0#
1"
#30000
1#
#40000
0!
0#
0"
1$
#50000
1!
1#
#60000
0!
0#
1"
#70000
1!
1#
