Lattice_iCEBreaker_v1.1a/9_active_low_voting_system_proj9/voting_system.v
/***************************************************
Engineer: Harrison Warke
Date Created: 26/10/2025
Module Name: voting_system
Project Name: LAoE
Target Device: Lattice ICE40UP5K-SG4k

Description: Create a voting system that allows 3 people (A,B and C) to vote
- each by pressing a normally open pushbutton in favour of a proposal - and
then lights one of four LEDs to indicate if none, one, two or three people 
voted for the proposition. All signals, inputs and outputs are active low. 
The inputs are pulled low by a push-button press, and the pin connected to
the external LEDs on the output side are pulled low when switched on.

Truth table below 

A  B  C |  No_Votes_LED  ONE_VOTE_LED  TWO_VOTES_LED  THREE_VOTES_LED
0  0  0 |     1               1              1                0
0  0  1 |     1               1              0                1
0  1  0 |     1               1              0                1
0  1  1 |     1               0              1                1
1  0  0 |     1               1              0                1
1  0  1 |     1               0              1                1
1  1  0 |     1               0              1                1
1  1  1 |     0               1              1                1


***************************************************/

module voting_system (
    input IN_A, 
    input IN_B, 
    input IN_C, 
    output NO_VOTES_LED,
    output ONE_VOTE_LED,
    output TWO_VOTES_LED,
    output THREE_VOTES_LED
);

//LED 'None' on (0) when no one votes (all inputs HIGH)
assign NO_VOTES_LED = ~(IN_A & IN_B & IN_C);

//LED 'One' on (0) when exactly ONE input is LOW
assign ONE_VOTE_LED = (~IN_A & ~IN_B) | (~IN_A & ~IN_C)  | (~IN_B & ~IN_C) | (IN_A & IN_B & IN_C);

//LED 'Two' on (0) when exactly two inputs are LOW
assign TWO_VOTES_LED = (IN_A & IN_B) | (IN_A & IN_C) | (IN_B & IN_C) | (~IN_A & ~IN_B & ~ IN_C);

//LED 'Three' on (0) when all three inputs are LOW
assign THREE_VOTES_LED = IN_A | IN_B | IN_C;

endmodule

Lattice_iCEBreaker_v1.1a/9_active_low_voting_system_proj9/voting_system_tb.v
`timescale 1ns/1ps

module voting_system_tb;

    // Testbench signals
    reg tb_IN_A;
    reg tb_IN_B;
    reg tb_IN_C;
    wire tb_NO_VOTES_LED;
    wire tb_ONE_VOTE_LED;
    wire tb_TWO_VOTES_LED;
    wire tb_THREE_VOTES_LED;

    // Instantiate the module under test
    voting_system uut (
        .IN_A(tb_IN_A),
        .IN_B(tb_IN_B),
        .IN_C(tb_IN_C),
        .NO_VOTES_LED(tb_NO_VOTES_LED),
        .ONE_VOTE_LED(tb_ONE_VOTE_LED),
        .TWO_VOTES_LED(tb_TWO_VOTES_LED),
        .THREE_VOTES_LED(tb_THREE_VOTES_LED)
    );

    initial begin
        // For GTKWave to dump waveform data
        $dumpfile("voting_system.vcd");      // Output VCD file
        $dumpvars(0, voting_system_tb); // Dump all variables in this scope

        $display("A  B  C | None    One    Two    Three");
        $monitor("%b  %b  %b |   %b      %b      %b      %b", 
            tb_IN_A, tb_IN_B, tb_IN_C, tb_NO_VOTES_LED, tb_ONE_VOTE_LED, tb_TWO_VOTES_LED, tb_THREE_VOTES_LED);
    

        // Test function of the three-way voting system 
     
        tb_IN_A = 0;
        tb_IN_B = 0;
        tb_IN_C = 0;
        #10;
        tb_IN_A = 0;
        tb_IN_B = 0;        
        tb_IN_C = 1;
        #10;
        tb_IN_A = 0;
        tb_IN_B = 1;        
        tb_IN_C = 0;
        #10;
        tb_IN_A = 0;
        tb_IN_B = 1;        
        tb_IN_C = 1;
        #10;
        tb_IN_A = 1;
        tb_IN_B = 0;        
        tb_IN_C = 0;
        #10;
        tb_IN_A = 1;
        tb_IN_B = 0;        
        tb_IN_C = 1;
        #10;
        tb_IN_A = 1;
        tb_IN_B = 1;        
        tb_IN_C = 0;
        #10;
        tb_IN_A = 1;
        tb_IN_B = 1;        
        tb_IN_C = 1;
        #10;
        $finish;  // End simulation
    end

endmodule

Lattice_iCEBreaker_v1.1a/9_active_low_voting_system_proj9/voting_system.vcd
$date
	Mon Oct 27 08:05:45 2025
$end
$version
	Icarus Verilog
$end
$timescale
	1ps
$end
$scope module voting_system_tb $end
$var wire 1 ! tb_TWO_VOTES_LED $end
$var wire 1 " tb_THREE_VOTES_LED $end
$var wire 1 # tb_ONE_VOTE_LED $end
$var wire 1 $ tb_NO_VOTES_LED $end
$var reg 1 % tb_IN_A $end
$var reg 1 & tb_IN_B $end
$var reg 1 ' tb_IN_C $end
$scope module uut $end
$var wire 1 % IN_A $end
$var wire 1 & IN_B $end
$var wire 1 ' IN_C $end
$var wire 1 $ NO_VOTES_LED $end
$var wire 1 # ONE_VOTE_LED $end
$var wire 1 " THREE_VOTES_LED $end
$var wire 1 ! TWO_VOTES_LED $end
$upscope $end
$upscope $end
$enddefinitions $end
$comment Show the parameter values. $end
$dumpall
$end
#0
$dumpvars
0'
0&
0%
1$
1#
0"
1!
$end
#10000
0!
1"
1'
#20000
0'
1&
#30000
0#
1!
1'
#40000
1#
0!
0'
0&
1%
#50000
0#
1!
1'
#60000
0'
1&
#70000
0$
1#
1'
